lyrpy/LUConsole.py
lyrpy/LUConst.py
lyrpy/LUDateTime.py
lyrpy/LUDecotators.py
lyrpy/LUDict.py
lyrpy/LUDoc.py
lyrpy/LUErrors.py
lyrpy/LUFile.py
lyrpy/LUFileUtils.py
lyrpy/LULog.py
lyrpy/LULogPySide6.py
lyrpy/LUNetwork.py
lyrpy/LUNumUtils.py
lyrpy/LUObjects.py
lyrpy/LUObjectsYT.py
lyrpy/LUParserARG.py
lyrpy/LUParserINI.py
lyrpy/LUParserREG.py
lyrpy/LUProc.py
lyrpy/LUQThread.py
lyrpy/LUQTimer.py
lyrpy/LUSheduler.py
lyrpy/LUStrDecode.py
lyrpy/LUStrUtils.py
lyrpy/LUSupport.py
lyrpy/LUTelegram.py
lyrpy/LUThread.py
lyrpy/LUTimer.py
lyrpy/LUVersion.py
lyrpy/LUYouTube.py
lyrpy/LUos.py
lyrpy/LUsys.py
lyrpy/__init__.py
lyrpy/logging.CONFIG
lyrpy/logging.INI
lyrpy/logging.YAML
lyrpy/logging_CONSOLE.INI
lyrpy/main.py
lyrpy/data/config.json
lyrpy/static/script.js
lyrpy/static/style.css
lyrpy/templates/1.txt
lyrpy/templates/template.html
lyrpy-2025.12.9.dist-info/licenses/LICENSE
lyrpy-2025.12.9.dist-info/METADATA
lyrpy-2025.12.9.dist-info/WHEEL
lyrpy-2025.12.9.dist-info/entry_points.txt
lyrpy-2025.12.9.dist-info/top_level.txt
lyrpy-2025.12.9.dist-info/RECORD
