Metadata-Version: 2.4
Name: lyrpy
Version: 2025.12.9
Summary: lyrpy
Home-page: https://github.com/lisitsinyr/TOOLS_SRC_PY
Author-email: lisitsinyr <lisitsinyr@gmail.com>
License-Expression: MIT
Keywords: sample,setuptools,development
Classifier: Programming Language :: Python :: 3.13
Classifier: Operating System :: OS Independent
Requires-Python: >=3.13
License-File: LICENSE
Requires-Dist: pip>=25.3
Requires-Dist: chardet>=5.2.0
Requires-Dist: colorama>=0.4.6
Requires-Dist: markdown-it-py>=4.0.0
Requires-Dist: mdurl>=0.1.2
Requires-Dist: psutil>=7.1.3
Requires-Dist: pyaes>=1.6.1
Requires-Dist: Pygments>=2.19.2
Requires-Dist: Pyrogram>=2.0.106
Requires-Dist: PySocks>=1.7.1
Requires-Dist: rich>=14.2.0
Requires-Dist: python-json-logger>=4.0.0
Requires-Dist: PyYAML>=6.0.3
Requires-Dist: build>=1.3.0
Requires-Dist: twine>=6.2.0
Provides-Extra: dev
Requires-Dist: check-manifest; extra == "dev"
Dynamic: home-page
Dynamic: license-file
Dynamic: requires-python
